nonebot_plugin_BiliMedalWall/__init__.py
nonebot_plugin_BiliMedalWall/api.py
nonebot_plugin_BiliMedalWall/draw.py
nonebot_plugin_BiliMedalWall/resources/fonts/LXGWWenKaiGB-Regular.ttf
nonebot_plugin_BiliMedalWall/resources/img/error.png
nonebot_plugin_BiliMedalWall-0.1.2.dist-info/LICENSE
nonebot_plugin_BiliMedalWall-0.1.2.dist-info/METADATA
nonebot_plugin_BiliMedalWall-0.1.2.dist-info/WHEEL
nonebot_plugin_BiliMedalWall-0.1.2.dist-info/top_level.txt
nonebot_plugin_BiliMedalWall-0.1.2.dist-info/RECORD
