Metadata-Version: 2.1
Name: nonebot-plugin-BiliMedalWall
Version: 0.1.2
Summary: Show BiliUsers MedalWall(info)
Home-page: https://github.com/Shadow403/nonebot_plugin_BiliMedalWall
Author: Shadow403
Author-email: admin@shadow403.cn
Classifier: Programming Language :: Python :: 3.11
Classifier: License :: OSI Approved :: MIT License
Classifier: Operating System :: OS Independent
Requires-Python: >=3.10
License-File: LICENSE
Requires-Dist: nonebot2 >=2.1.2
Requires-Dist: nonebot-adapter-onebot >=2.3.1
Requires-Dist: requests >=2.31.0
Requires-Dist: jsonpath >=0.82.2
Requires-Dist: matplotlib >=3.8.1
Requires-Dist: pathlib >=1.0.1
